LICENSE
MANIFEST.in
README.markdown
local-requirements.txt
requirements.txt
setup.py
sanetime/__init__.py
sanetime/constants.py
sanetime/dj.py
sanetime/error.py
sanetime/sanedelta.py
sanetime/sanespan.py
sanetime/sanetime.py
sanetime/sanetztime.py
sanetime.egg-info/PKG-INFO
sanetime.egg-info/SOURCES.txt
sanetime.egg-info/dependency_links.txt
sanetime.egg-info/requires.txt
sanetime.egg-info/top_level.txt
sanetime/test/__init__.py
sanetime/test/test_delta.py
sanetime/test/test_time.py
sanetime/test/test_tztime.py