Metadata-Version: 1.0
Name: sanetime
Version: 4.2.3
Summary: A sane date/time python interface:  better epoch time, timezones, and deltas -- django support as well
Home-page: http://hubspot.github.com/sanetime/
Author: prior
Author-email: mprior@hubspot.com
License: Copyright (c) 2012 HubSpot, Inc.
